__init__.py
obanalyser/__init__.py
obanalyser/analyse_build.py
obanalyser/analyse_obf_geometry.py
obanalyser/analyse_obp.py
obanalyser/analyse_obp_geometry.py
obanalyser/config.py
obanalyser/data_classes.py
obanalyser/extract_obp_elements.py
obanalyser/get_3mf_data.py
obanalyser/get_build_order.py
obanalyser/obr/__init__.py
obanalyser/obr/analyse_obr.py
obanalyser/obr/exposure.py
obanalyser/obr/layer_heights.py
obanalyser/obr/recoate_times.py
obanalyser/obr/temperatures.py
obanalyser/obr/write_db.py
obanalyser/plotters/plot_build_data.py
obanalyser/plotters/plot_csv.py
obanalyser/plotters/plot_obp_img.py
obpanalyser-0.0.11.dist-info/licenses/LICENSE
obpanalyser-0.0.11.dist-info/METADATA
obpanalyser-0.0.11.dist-info/WHEEL
obpanalyser-0.0.11.dist-info/top_level.txt
obpanalyser-0.0.11.dist-info/RECORD
