Metadata-Version: 2.4
Name: OBPAnalyser
Version: 0.0.11
Summary: A package for analysation of open beam files (OBP and OBF).
Author-email: Anton Wiberg <wiberg.anton@gmail.com>
License: MIT
Project-URL: Homepage, https://github.com/wiberganton/OBAnalyser
Project-URL: Repository, https://github.com/wiberganton/OBAnalyser
Requires-Python: >=3.7
License-File: LICENSE
Requires-Dist: obplib
Requires-Dist: numpy
Requires-Dist: py3mf_slicer
Requires-Dist: matplotlib
Requires-Dist: scipy
Requires-Dist: pandas
Requires-Dist: pyyaml
Dynamic: license-file
